{
  "id": "84847d83-17ba-4d57-829f-326c72a8bc44",
  "prevId": "71d0b340-116a-4f43-8868-8c59b75510d2",
  "version": "7",
  "dialect": "postgresql",
  "tables": {
    "public.app_installations": {
      "name": "app_installations",
      "schema": "",
      "columns": {
        "id": {
          "name": "id",
          "type": "uuid",
          "primaryKey": true,
          "notNull": true,
          "default": "gen_random_uuid()"
        },
        "created_at": {
          "name": "created_at",
          "type": "timestamp with time zone",
          "primaryKey": false,
          "notNull": true,
          "default": "now()"
        }
      },
      "indexes": {},
      "foreignKeys": {},
      "compositePrimaryKeys": {},
      "uniqueConstraints": {},
      "policies": {},
      "checkConstraints": {},
      "isRLSEnabled": false
    },
    "public.canvas_owners": {
      "name": "canvas_owners",
      "schema": "",
      "columns": {
        "id": {
          "name": "id",
          "type": "uuid",
          "primaryKey": true,
          "notNull": true,
          "default": "gen_random_uuid()"
        },
        "owner_session_hash": {
          "name": "owner_session_hash",
          "type": "text",
          "primaryKey": false,
          "notNull": true
        },
        "canvas_id": {
          "name": "canvas_id",
          "type": "uuid",
          "primaryKey": false,
          "notNull": true
        },
        "created_at": {
          "name": "created_at",
          "type": "timestamp with time zone",
          "primaryKey": false,
          "notNull": true,
          "default": "now()"
        }
      },
      "indexes": {
        "canvas_owners_owner_session_canvas_idx": {
          "name": "canvas_owners_owner_session_canvas_idx",
          "columns": [
            {
              "expression": "owner_session_hash",
              "isExpression": false,
              "asc": true,
              "nulls": "last"
            },
            {
              "expression": "canvas_id",
              "isExpression": false,
              "asc": true,
              "nulls": "last"
            }
          ],
          "isUnique": true,
          "concurrently": false,
          "method": "btree",
          "with": {}
        }
      },
      "foreignKeys": {
        "canvas_owners_canvas_id_canvases_id_fk": {
          "name": "canvas_owners_canvas_id_canvases_id_fk",
          "tableFrom": "canvas_owners",
          "tableTo": "canvases",
          "columnsFrom": [
            "canvas_id"
          ],
          "columnsTo": [
            "id"
          ],
          "onDelete": "cascade",
          "onUpdate": "no action"
        }
      },
      "compositePrimaryKeys": {},
      "uniqueConstraints": {},
      "policies": {},
      "checkConstraints": {},
      "isRLSEnabled": false
    },
    "public.canvases": {
      "name": "canvases",
      "schema": "",
      "columns": {
        "id": {
          "name": "id",
          "type": "uuid",
          "primaryKey": true,
          "notNull": true,
          "default": "gen_random_uuid()"
        },
        "public_token": {
          "name": "public_token",
          "type": "text",
          "primaryKey": false,
          "notNull": true
        },
        "owner_token_hash": {
          "name": "owner_token_hash",
          "type": "text",
          "primaryKey": false,
          "notNull": true
        },
        "status": {
          "name": "status",
          "type": "text",
          "primaryKey": false,
          "notNull": true,
          "default": "'waiting'"
        },
        "last_viewed_at": {
          "name": "last_viewed_at",
          "type": "timestamp with time zone",
          "primaryKey": false,
          "notNull": false
        },
        "created_at": {
          "name": "created_at",
          "type": "timestamp with time zone",
          "primaryKey": false,
          "notNull": true,
          "default": "now()"
        },
        "updated_at": {
          "name": "updated_at",
          "type": "timestamp with time zone",
          "primaryKey": false,
          "notNull": true,
          "default": "now()"
        }
      },
      "indexes": {},
      "foreignKeys": {},
      "compositePrimaryKeys": {},
      "uniqueConstraints": {
        "canvases_public_token_unique": {
          "name": "canvases_public_token_unique",
          "nullsNotDistinct": false,
          "columns": [
            "public_token"
          ]
        }
      },
      "policies": {},
      "checkConstraints": {},
      "isRLSEnabled": false
    },
    "public.participants": {
      "name": "participants",
      "schema": "",
      "columns": {
        "id": {
          "name": "id",
          "type": "uuid",
          "primaryKey": true,
          "notNull": true,
          "default": "gen_random_uuid()"
        },
        "canvas_id": {
          "name": "canvas_id",
          "type": "uuid",
          "primaryKey": false,
          "notNull": true
        },
        "slot": {
          "name": "slot",
          "type": "smallint",
          "primaryKey": false,
          "notNull": true
        },
        "display_name": {
          "name": "display_name",
          "type": "text",
          "primaryKey": false,
          "notNull": true
        },
        "private_session_token_hash": {
          "name": "private_session_token_hash",
          "type": "text",
          "primaryKey": false,
          "notNull": true
        },
        "completed_at": {
          "name": "completed_at",
          "type": "timestamp with time zone",
          "primaryKey": false,
          "notNull": false
        },
        "created_at": {
          "name": "created_at",
          "type": "timestamp with time zone",
          "primaryKey": false,
          "notNull": true,
          "default": "now()"
        }
      },
      "indexes": {
        "participants_private_session_token_hash_idx": {
          "name": "participants_private_session_token_hash_idx",
          "columns": [
            {
              "expression": "private_session_token_hash",
              "isExpression": false,
              "asc": true,
              "nulls": "last"
            }
          ],
          "isUnique": true,
          "concurrently": false,
          "method": "btree",
          "with": {}
        },
        "participants_canvas_slot_idx": {
          "name": "participants_canvas_slot_idx",
          "columns": [
            {
              "expression": "canvas_id",
              "isExpression": false,
              "asc": true,
              "nulls": "last"
            },
            {
              "expression": "slot",
              "isExpression": false,
              "asc": true,
              "nulls": "last"
            }
          ],
          "isUnique": true,
          "concurrently": false,
          "method": "btree",
          "with": {}
        }
      },
      "foreignKeys": {
        "participants_canvas_id_canvases_id_fk": {
          "name": "participants_canvas_id_canvases_id_fk",
          "tableFrom": "participants",
          "tableTo": "canvases",
          "columnsFrom": [
            "canvas_id"
          ],
          "columnsTo": [
            "id"
          ],
          "onDelete": "cascade",
          "onUpdate": "no action"
        }
      },
      "compositePrimaryKeys": {},
      "uniqueConstraints": {},
      "policies": {},
      "checkConstraints": {
        "participants_slot_check": {
          "name": "participants_slot_check",
          "value": "\"participants\".\"slot\" in (1, 2)"
        }
      },
      "isRLSEnabled": false
    },
    "public.responses": {
      "name": "responses",
      "schema": "",
      "columns": {
        "id": {
          "name": "id",
          "type": "uuid",
          "primaryKey": true,
          "notNull": true,
          "default": "gen_random_uuid()"
        },
        "participant_id": {
          "name": "participant_id",
          "type": "uuid",
          "primaryKey": false,
          "notNull": true
        },
        "reflection_id": {
          "name": "reflection_id",
          "type": "text",
          "primaryKey": false,
          "notNull": true
        },
        "response_text": {
          "name": "response_text",
          "type": "text",
          "primaryKey": false,
          "notNull": true
        },
        "created_at": {
          "name": "created_at",
          "type": "timestamp with time zone",
          "primaryKey": false,
          "notNull": true,
          "default": "now()"
        }
      },
      "indexes": {
        "responses_participant_reflection_idx": {
          "name": "responses_participant_reflection_idx",
          "columns": [
            {
              "expression": "participant_id",
              "isExpression": false,
              "asc": true,
              "nulls": "last"
            },
            {
              "expression": "reflection_id",
              "isExpression": false,
              "asc": true,
              "nulls": "last"
            }
          ],
          "isUnique": true,
          "concurrently": false,
          "method": "btree",
          "with": {}
        }
      },
      "foreignKeys": {
        "responses_participant_id_participants_id_fk": {
          "name": "responses_participant_id_participants_id_fk",
          "tableFrom": "responses",
          "tableTo": "participants",
          "columnsFrom": [
            "participant_id"
          ],
          "columnsTo": [
            "id"
          ],
          "onDelete": "cascade",
          "onUpdate": "no action"
        }
      },
      "compositePrimaryKeys": {},
      "uniqueConstraints": {},
      "policies": {},
      "checkConstraints": {},
      "isRLSEnabled": false
    }
  },
  "enums": {},
  "schemas": {},
  "sequences": {},
  "roles": {},
  "policies": {},
  "views": {},
  "_meta": {
    "columns": {},
    "schemas": {},
    "tables": {}
  }
}